netbayesabm/__init__.py
netbayesabm/classes.py
netbayesabm/data_analysis.py
netbayesabm/modelling.py
netbayesabm/visualization.py
netbayesabm/abc_module/__init__.py
netbayesabm/abc_module/metrics.py
netbayesabm-0.1.2.dist-info/licenses/LICENSE
netbayesabm-0.1.2.dist-info/METADATA
netbayesabm-0.1.2.dist-info/WHEEL
netbayesabm-0.1.2.dist-info/top_level.txt
netbayesabm-0.1.2.dist-info/RECORD
