Metadata-Version: 2.4
Name: netbayesabm
Version: 0.1.2
Summary: Agent-based models of plant–pollinator networks with Bayesian inference (ABC).
Author-email: "Javier Galeano, " <javier.galeano@upm.es>, "Blanca Arroyo-Correa, " <blanca.arroyo@ebd.csic.es>, "Mario Castro, " <marioc@iit.comillas.edu>
Maintainer-email: Javier Galeano <javier.galeano@upm.es>
License: MIT
Project-URL: Homepage, https://github.com/galeanojav/NetBayesABM
Project-URL: Repository, https://github.com/galeanojav/NetBayesABM
Project-URL: Issues, https://github.com/galeanojav/NetBayesABM/issues
Keywords: abm,ecology,pollination,bayesian,abc
Classifier: Programming Language :: Python :: 3
Classifier: License :: OSI Approved :: MIT License
Classifier: Topic :: Scientific/Engineering
Requires-Python: >=3.9
License-File: LICENSE
Requires-Dist: numpy
Requires-Dist: pandas
Requires-Dist: matplotlib
Requires-Dist: seaborn
Requires-Dist: networkx
Requires-Dist: scipy
Dynamic: license-file
